{
  "formats": [
    {
      "id": "asdd",
      "user": "dare",
      "format": [
        "XXXI+XXXXX",
        "XXXXXXXXXX",
        "XXXXXXXXXX"
      ]
    },
    {
      "id": "da",
      "user": "dare",
      "format": [
        "XXXLXXXXXX",
        "XXXXXXXXXX",
        "XXXXXXXXXX"
      ]
    },
    {
      "id": "d",
      "user": "asd",
      "format": [
        "XXXLIXXXXX",
        "XXXXXXXXXX",
        "XXXXXXXXXX"
      ]
    },
    {
      "id": "asd",
      "user": "asd",
      "format": [
        "XXXXXXXXXX",
        "XXXXXXXXXX",
        "XXXXXXXXXX"
      ]
    },
    {
      "id": "asddd",
      "user": "dare",
      "format": [
        "XXXXPLXXXX",
        "XXXXXXXXXX",
        "XXXXXXXXXX"
      ]
    },
    {
      "id": "dd",
      "user": "dare",
      "format": [
        "XXXXXXXXXX",
        "XXXXXXXXXX",
        "XXXXXXXXXX"
      ]
    }
  ],
  "users": [
    {
      "id": "damjan",
      "password": "asd",
      "superUser": false,
      "subjects": [
        {
          "text": "asd",
          "scale": {
            "rows": 3,
            "cols": 10,
            "format": [
              "XXXXXXXXXX",
              "XXXXXXXXXX",
              "XXXXXXXXXX"
            ]
          }
        },
        {
          "text": "asdd",
          "scale": {
            "rows": 3,
            "cols": 10,
            "format": [
              "XXXXXXXXXX",
              "XXXXXXXXXX",
              "XXXXXXXXXX"
            ]
          }
        }
      ]
    },
    {
      "id": "dare",
      "password": "asd",
      "superUser": true,
      "subjects": [
        {
          "text": "asdd",
          "scale": {
            "rows": 3,
            "cols": 10,
            "format": [
              "XXXI+XXXXX",
              "XXXXXXXXXX",
              "XXXXXXXXXX"
            ],
            "points": [
              [
                "X",
                "X",
                "X",
                "X",
                "X",
                "X",
                "X",
                "X",
                "X",
                "X"
              ],
              [
                "X",
                "X",
                "X",
                "X",
                "X",
                "X",
                "X",
                "X",
                "X",
                "X"
              ],
              [
                "X",
                "X",
                "X",
                "X",
                "X",
                "X",
                "X",
                "X",
                "X",
                "X"
              ]
            ]
          }
        },
        {
          "text": "da",
          "scale": {
            "rows": 3,
            "cols": 10,
            "format": [
              "XXXLXXXXXX",
              "XXXXXXXXXX",
              "XXXXXXXXXX"
            ],
            "points": [
              [
                "X",
                "X",
                "X",
                "X",
                "X",
                "X",
                "X",
                "X",
                "X",
                "X"
              ],
              [
                "X",
                "X",
                "X",
                "X",
                "X",
                "X",
                "X",
                "X",
                "X",
                "X"
              ],
              [
                "X",
                "X",
                "X",
                "X",
                "X",
                "X",
                "X",
                "X",
                "X",
                "X"
              ]
            ]
          }
        },
        {
          "text": "asddd",
          "scale": {
            "rows": 3,
            "cols": 10,
            "format": [
              "XXXXPLXXXX",
              "XXXXXXXXXX",
              "XXXXXXXXXX"
            ],
            "points": [
              [
                "X",
                "X",
                "X",
                "X",
                "X",
                "X",
                "X",
                "X",
                "X",
                "X"
              ],
              [
                "X",
                "X",
                "X",
                "X",
                "X",
                "X",
                "X",
                "X",
                "X",
                "X"
              ],
              [
                "X",
                "X",
                "X",
                "X",
                "X",
                "X",
                "X",
                "X",
                "X",
                "X"
              ]
            ]
          }
        },
        {
          "text": "dd",
          "scale": {
            "rows": 3,
            "cols": 10,
            "format": [
              "XXXXXXXXXX",
              "XXXXXXXXXX",
              "XXXXXXXXXX"
            ]
          }
        }
      ]
    },
    {
      "id": "asd",
      "password": "asd",
      "superUser": true,
      "subjects": [
        {
          "text": "d",
          "scale": {
            "rows": 3,
            "cols": 10,
            "format": [
              "XXXLIXXXXX",
              "XXXXXXXXXX",
              "XXXXXXXXXX"
            ],
            "points": [
              [
                "X",
                "X",
                "X",
                "X",
                "X",
                "X",
                "X",
                "X",
                "X",
                "X"
              ],
              [
                "X",
                "X",
                "X",
                "X",
                "X",
                "X",
                "X",
                "X",
                "X",
                "X"
              ],
              [
                "X",
                "X",
                "X",
                "X",
                "X",
                "X",
                "X",
                "X",
                "X",
                "X"
              ]
            ]
          }
        },
        {
          "text": "asd",
          "scale": {
            "rows": 3,
            "cols": 10,
            "format": [
              "XXXXXXXXXX",
              "XXXXXXXXXX",
              "XXXXXXXXXX"
            ]
          }
        }
      ]
    }
  ]
}